{
    "actions": [],
    "allow_rename": 1,
    "autoname": "hash",
    "creation": "2025-12-28 20:00:00.000000",
    "doctype": "DocType",
    "editable_grid": 1,
    "engine": "InnoDB",
    "field_order": [
        "title",
        "route",
        "section",
        "icon",
        "role"
    ],
    "fields": [
        {
            "fieldname": "title",
            "fieldtype": "Data",
            "in_list_view": 1,
            "label": "Title",
            "reqd": 1
        },
        {
            "fieldname": "route",
            "fieldtype": "Data",
            "in_list_view": 1,
            "label": "Route",
            "reqd": 1
        },
        {
            "fieldname": "section",
            "fieldtype": "Data",
            "in_list_view": 1,
            "label": "Section"
        },
        {
            "fieldname": "icon",
            "fieldtype": "Data",
            "label": "Icon (Feather Name)"
        },
        {
            "fieldname": "role",
            "fieldtype": "Link",
            "label": "Required Role",
            "options": "Role"
        }
    ],
    "index_web_pages_for_search": 1,
    "istable": 1,
    "links": [],
    "modified": "2025-12-28 20:00:00.000000",
    "modified_by": "Administrator",
    "module": "Portal RRHH",
    "name": "Portal HR Sidebar Item",
    "owner": "Administrator",
    "permissions": [],
    "sort_field": "modified",
    "sort_order": "DESC",
    "states": []
}